{"commitInfo":{"timestamp":1756868754162,"operation":"WRITE","operationParameters":{"mode":"Append","partitionBy":"[]"},"readVersion":9,"isolationLevel":"Serializable","isBlindAppend":true,"operationMetrics":{"numFiles":"1","numOutputRows":"1","numOutputBytes":"1353"},"engineInfo":"Apache-Spark/3.5.1 Delta-Lake/3.2.0","txnId":"66a0ebb7-3433-4f4c-95cd-802eac5609d8"}}
{"add":{"path":"event_date=2025-09-02/part-00000-0e8a20d8-160b-41f3-80d4-26992c497dc4.c000.snappy.parquet","partitionValues":{"event_date":"2025-09-02"},"size":1353,"modificationTime":1756868754158,"dataChange":true,"stats":"{\"numRecords\":1,\"minValues\":{\"order_id\":\"o_demo_2\",\"customer_id\":\"c_001\",\"order_status\":\"approved\",\"event_ts_ms\":1756868754000},\"maxValues\":{\"order_id\":\"o_demo_2\",\"customer_id\":\"c_001\",\"order_status\":\"approved\",\"event_ts_ms\":1756868754000},\"nullCount\":{\"order_id\":0,\"customer_id\":0,\"order_status\":0,\"event_ts_ms\":0}}"}}
